asyncfix/__init__.py
asyncfix/codec.py
asyncfix/connection.py
asyncfix/connection_client.py
asyncfix/connection_server.py
asyncfix/errors.py
asyncfix/fix_tester.py
asyncfix/fixtags.py
asyncfix/journaler.py
asyncfix/message.py
asyncfix/msgtype.py
asyncfix/session.py
asyncfix/protocol/__init__.py
asyncfix/protocol/common.py
asyncfix/protocol/order_single.py
asyncfix/protocol/protocol_base.py
asyncfix/protocol/protocol_fix44.py
asyncfix/protocol/schema.py
asyncfix-1.0.1.dist-info/LICENSE
asyncfix-1.0.1.dist-info/METADATA
asyncfix-1.0.1.dist-info/WHEEL
asyncfix-1.0.1.dist-info/top_level.txt
asyncfix-1.0.1.dist-info/RECORD
