Metadata-Version: 2.1
Name: asyncfix
Version: 1.0.1
Summary: AsyncIO FIX Protocol client for Python
Author-email: Alex Veden <i@alexveden.com>
License: MIT License
Project-URL: Homepage, https://github.com/alexveden/asyncfix
Keywords: asyncio,FIX,protocol,client,server,parser,unit tests,simplefix,tester,orders
Classifier: License :: OSI Approved :: MIT License
Classifier: Programming Language :: Python
Classifier: Programming Language :: Python :: 3.8
Classifier: Development Status :: 5 - Production/Stable
Requires-Python: >=3.8
License-File: LICENSE
Provides-Extra: dev
Requires-Dist: pytest; extra == "dev"
Requires-Dist: isort==5.12.0; extra == "dev"
Requires-Dist: flake8==6.1.0; extra == "dev"
Requires-Dist: black==23.7.0; extra == "dev"
Requires-Dist: pre-commit; extra == "dev"
Requires-Dist: pytest-asyncio; extra == "dev"
Requires-Dist: lazydocs; extra == "dev"
Requires-Dist: pydocstringformatter; extra == "dev"
Requires-Dist: pydocstyle; extra == "dev"
Requires-Dist: toml; extra == "dev"
Requires-Dist: mkdocs; extra == "dev"
